{
   "113203": [
      {
         "x": 6479,
         "y": 2891,
         "person": "person1",
         "session": "S2",
         "phase": 1,
         "quartiles": 4,
         "angle": 85.0959648,
         "interpolated": 0,
         "CI": "Callthedoctor",
         "id": "one"
      },
      {
         "x": 6354.5,
         "y": 2968,
         "person": "person2",
         "session": "S2",
         "phase": 1,
         "quartiles": 4,
         "angle": -75.7333458,
         "interpolated": 1,
         "CI": "Callthedoctor",
         "id": "two"
      },
      {
         "x": 5983,
         "y": 2926,
         "person": "person3",
         "session": "S2",
         "phase": 1,
         "quartiles": 4,
         "angle": -27.834057,
         "interpolated": 0,
         "CI": "Callthedoctor",
         "id": "three"
      }
   ],
   "113204": [
      {
         "x": 6479,
         "y": 2797,
         "person": "person1",
         "session": "S2",
         "phase": 1,
         "quartiles": 4,
         "angle": -265.8408102,
         "interpolated": 0,
         "CI": "Callthedoctor",
         "id": "one"
      },
      {
         "x": 6370,
         "y": 2903,
         "person": "person2",
         "session": "S2",
         "phase": 1,
         "quartiles": 4,
         "angle": -78.7700232,
         "interpolated": 0,
         "CI": "Callthedoctor",
         "id": "two"
      },
      {
         "x": 6080,
         "y": 3125,
         "person": "person3",
         "session": "S2",
         "phase": 1,
         "quartiles": 4,
         "angle": -27.834057,
         "interpolated": 0,
         "CI": "Callthedoctor",
         "id": "three"
      }
   ],
   "113205": [
      {
         "x": 6612,
         "y": 2699,
         "person": "person1",
         "session": "S2",
         "phase": 1,
         "quartiles": 4,
         "angle": 92.1433482,
         "interpolated": 0,
         "CI": "Callthedoctor",
         "id": "one"
      },
      {
         "x": 6441,
         "y": 3033,
         "person": "person2",
         "session": "S2",
         "phase": 1,
         "quartiles": 4,
         "angle": -79.4575728,
         "interpolated": 0,
         "CI": "Callthedoctor",
         "id": "two"
      },
      {
         "x": 6017,
         "y": 3441,
         "person": "person3",
         "session": "S2",
         "phase": 1,
         "quartiles": 4,
         "angle": -27.834057,
         "interpolated": 0,
         "CI": "Callthedoctor",
         "id": "three"
      }
   ],
   "113206": [
      {
         "x": 6652,
         "y": 2699,
         "person": "person1",
         "session": "S2",
         "phase": 1,
         "quartiles": 4,
         "angle": -263.9500488,
         "interpolated": 0,
         "CI": "Callthedoctor",
         "id": "one"
      },
      {
         "x": 6494,
         "y": 3152,
         "person": "person2",
         "session": "S2",
         "phase": 1,
         "quartiles": 4,
         "angle": -78.5981358,
         "interpolated": 0,
         "CI": "Callthedoctor",
         "id": "two"
      },
      {
         "x": 6014,
         "y": 3709,
         "person": "person3",
         "session": "S2",
         "phase": 1,
         "quartiles": 4,
         "angle": -27.834057,
         "interpolated": 0,
         "CI": "Callthedoctor",
         "id": "three"
      }
   ],
   "113207": [
      {
         "x": 6804,
         "y": 2607,
         "person": "person1",
         "session": "S2",
         "phase": 1,
         "quartiles": 4,
         "angle": -265.2678522,
         "interpolated": 0,
         "CI": "Callthedoctor",
         "id": "one"
      },
      {
         "x": 6494,
         "y": 3152,
         "person": "person2",
         "session": "S2",
         "phase": 1,
         "quartiles": 4,
         "angle": -78.5981358,
         "interpolated": 1,
         "CI": "Callthedoctor",
         "id": "two"
      },
      {
         "x": 6171,
         "y": 3856,
         "person": "person3",
         "session": "S2",
         "phase": 1,
         "quartiles": 4,
         "angle": -27.834057,
         "interpolated": 1,
         "CI": "Callthedoctor",
         "id": "three"
      }
   ],
   "113208": [
      {
         "x": 6652,
         "y": 2607,
         "person": "person1",
         "session": "S2",
         "phase": 1,
         "quartiles": 4,
         "angle": 93.1173768,
         "interpolated": 0,
         "CI": "Callthedoctor",
         "id": "one"
      },
      {
         "x": 6494,
         "y": 3152,
         "person": "person2",
         "session": "S2",
         "phase": 1,
         "quartiles": 4,
         "angle": -79.2283896,
         "interpolated": 0,
         "CI": "Callthedoctor",
         "id": "two"
      },
      {
         "x": 6276,
         "y": 3856,
         "person": "person3",
         "session": "S2",
         "phase": 1,
         "quartiles": 4,
         "angle": -27.834057,
         "interpolated": 0,
         "CI": "Callthedoctor",
         "id": "three"
      }
   ],
   "113209": [
      {
         "x": 6804,
         "y": 2708,
         "person": "person1",
         "session": "S2",
         "phase": 1,
         "quartiles": 4,
         "angle": -265.2105564,
         "interpolated": 0,
         "CI": "Callthedoctor",
         "id": "one"
      },
      {
         "x": 6494,
         "y": 3152,
         "person": "person2",
         "session": "S2",
         "phase": 1,
         "quartiles": 4,
         "angle": -79.3429812,
         "interpolated": 0,
         "CI": "Callthedoctor",
         "id": "two"
      },
      {
         "x": 6375,
         "y": 3856,
         "person": "person3",
         "session": "S2",
         "phase": 1,
         "quartiles": 4,
         "angle": -27.834057,
         "interpolated": 0,
         "CI": "Callthedoctor",
         "id": "three"
      }
   ],
   "113210": [
      {
         "x": 6879,
         "y": 2804,
         "person": "person1",
         "session": "S2",
         "phase": 1,
         "quartiles": 4,
         "angle": 93.919518,
         "interpolated": 0,
         "CI": "Callthedoctor",
         "id": "one"
      },
      {
         "x": 6455,
         "y": 3112,
         "person": "person2",
         "session": "S2",
         "phase": 1,
         "quartiles": 4,
         "angle": -79.400277,
         "interpolated": 0,
         "CI": "Callthedoctor",
         "id": "two"
      },
      {
         "x": 6512,
         "y": 3514,
         "person": "person3",
         "session": "S2",
         "phase": 1,
         "quartiles": 4,
         "angle": -27.834057,
         "interpolated": 0,
         "CI": "Callthedoctor",
         "id": "three"
      }
   ],
   "113211": [
      {
         "x": 6879,
         "y": 2778,
         "person": "person1",
         "session": "S2",
         "phase": 1,
         "quartiles": 4,
         "angle": 93.1173768,
         "interpolated": 0,
         "CI": "Callthedoctor",
         "id": "one"
      },
      {
         "x": 6455,
         "y": 3112,
         "person": "person2",
         "session": "S2",
         "phase": 1,
         "quartiles": 4,
         "angle": -79.400277,
         "interpolated": 1,
         "CI": "Callthedoctor",
         "id": "two"
      },
      {
         "x": 6748,
         "y": 3146,
         "person": "person3",
         "session": "S2",
         "phase": 1,
         "quartiles": 4,
         "angle": -27.834057,
         "interpolated": 0,
         "CI": "Callthedoctor",
         "id": "three"
      }
   ],
   "113212": [
      {
         "x": 6761,
         "y": 2810,
         "person": "person1",
         "session": "S2",
         "phase": 1,
         "quartiles": 4,
         "angle": 93.8049264,
         "interpolated": 0,
         "CI": "Callthedoctor",
         "id": "one"
      },
      {
         "x": 6455,
         "y": 3112,
         "person": "person2",
         "session": "S2",
         "phase": 1,
         "quartiles": 4,
         "angle": -77.2803324,
         "interpolated": 0,
         "CI": "Callthedoctor",
         "id": "two"
      },
      {
         "x": 6914,
         "y": 3018,
         "person": "person3",
         "session": "S2",
         "phase": 1,
         "quartiles": 4,
         "angle": -27.834057,
         "interpolated": 0,
         "CI": "Callthedoctor",
         "id": "three"
      }
   ],
   "113213": [
      {
         "x": 6761,
         "y": 2810,
         "person": "person1",
         "session": "S2",
         "phase": 1,
         "quartiles": 4,
         "angle": -266.0126976,
         "interpolated": 0,
         "CI": "Callthedoctor",
         "id": "one"
      },
      {
         "x": 6455,
         "y": 3119.5,
         "person": "person2",
         "session": "S2",
         "phase": 1,
         "quartiles": 4,
         "angle": -77.2803324,
         "interpolated": 1,
         "CI": "Callthedoctor",
         "id": "two"
      },
      {
         "x": 6886.333333,
         "y": 3012.166667,
         "person": "person3",
         "session": "S2",
         "phase": 1,
         "quartiles": 4,
         "angle": -27.834057,
         "interpolated": 1,
         "CI": "Callthedoctor",
         "id": "three"
      }
   ],
   "113214": [
      {
         "x": 6519,
         "y": 2709,
         "person": "person1",
         "session": "S2",
         "phase": 1,
         "quartiles": 4,
         "angle": -265.6689228,
         "interpolated": 0,
         "CI": "Callthedoctor",
         "id": "one"
      },
      {
         "x": 6455,
         "y": 3127,
         "person": "person2",
         "session": "S2",
         "phase": 1,
         "quartiles": 4,
         "angle": -86.1038856,
         "interpolated": 0,
         "CI": "Callthedoctor",
         "id": "two"
      },
      {
         "x": 6858.666667,
         "y": 3006.333333,
         "person": "person3",
         "session": "S2",
         "phase": 1,
         "quartiles": 4,
         "angle": -27.834057,
         "interpolated": 1,
         "CI": "Callthedoctor",
         "id": "three"
      }
   ],
   "113215": [
      {
         "x": 6256,
         "y": 2560,
         "person": "person1",
         "session": "S2",
         "phase": 1,
         "quartiles": 4,
         "angle": -264.6948942,
         "interpolated": 0,
         "CI": "Callthedoctor",
         "id": "one"
      },
      {
         "x": 6481,
         "y": 3127,
         "person": "person2",
         "session": "S2",
         "phase": 1,
         "quartiles": 4,
         "angle": -63.357453,
         "interpolated": 0,
         "CI": "Callthedoctor",
         "id": "two"
      },
      {
         "x": 6831,
         "y": 3000.5,
         "person": "person3",
         "session": "S2",
         "phase": 1,
         "quartiles": 4,
         "angle": -27.834057,
         "interpolated": 1,
         "CI": "Callthedoctor",
         "id": "three"
      }
   ],
   "113216": [
      {
         "x": 6256,
         "y": 2560,
         "person": "person1",
         "session": "S2",
         "phase": 1,
         "quartiles": 4,
         "angle": -264.2938236,
         "interpolated": 0,
         "CI": "Callthedoctor",
         "id": "one"
      },
      {
         "x": 6548,
         "y": 3082,
         "person": "person2",
         "session": "S2",
         "phase": 1,
         "quartiles": 4,
         "angle": -52.8150258,
         "interpolated": 0,
         "CI": "Callthedoctor",
         "id": "two"
      },
      {
         "x": 6803.333333,
         "y": 2994.666667,
         "person": "person3",
         "session": "S2",
         "phase": 1,
         "quartiles": 4,
         "angle": -27.834057,
         "interpolated": 1,
         "CI": "Callthedoctor",
         "id": "three"
      }
   ],
   "113217": [
      {
         "x": 6256,
         "y": 2560,
         "person": "person1",
         "session": "S2",
         "phase": 1,
         "quartiles": 4,
         "angle": -264.5803026,
         "interpolated": 0,
         "CI": "Callthedoctor",
         "id": "one"
      },
      {
         "x": 6568,
         "y": 3066,
         "person": "person2",
         "session": "S2",
         "phase": 1,
         "quartiles": 4,
         "angle": -59.633226,
         "interpolated": 0,
         "CI": "Callthedoctor",
         "id": "two"
      },
      {
         "x": 6775.666667,
         "y": 2988.833333,
         "person": "person3",
         "session": "S2",
         "phase": 1,
         "quartiles": 4,
         "angle": -27.834057,
         "interpolated": 1,
         "CI": "Callthedoctor",
         "id": "three"
      }
   ],
   "113218": [
      {
         "x": 6210,
         "y": 2449,
         "person": "person1",
         "session": "S2",
         "phase": 1,
         "quartiles": 4,
         "angle": -264.4084152,
         "interpolated": 0,
         "CI": "Callthedoctor",
         "id": "one"
      },
      {
         "x": 6577,
         "y": 3013.5,
         "person": "person2",
         "session": "S2",
         "phase": 1,
         "quartiles": 4,
         "angle": -59.633226,
         "interpolated": 1,
         "CI": "Callthedoctor",
         "id": "two"
      },
      {
         "x": 6748,
         "y": 2983,
         "person": "person3",
         "session": "S2",
         "phase": 1,
         "quartiles": 4,
         "angle": -27.834057,
         "interpolated": 0,
         "CI": "Callthedoctor",
         "id": "three"
      }
   ],
   "113219": [
      {
         "x": 6351,
         "y": 2510,
         "person": "person1",
         "session": "S2",
         "phase": 1,
         "quartiles": 4,
         "angle": -263.319795,
         "interpolated": 0,
         "CI": "Callthedoctor",
         "id": "one"
      },
      {
         "x": 6586,
         "y": 2961,
         "person": "person2",
         "session": "S2",
         "phase": 1,
         "quartiles": 4,
         "angle": -63.5866362,
         "interpolated": 0,
         "CI": "Callthedoctor",
         "id": "two"
      },
      {
         "x": 6758.3,
         "y": 2969.9,
         "person": "person3",
         "session": "S2",
         "phase": 1,
         "quartiles": 4,
         "angle": -27.834057,
         "interpolated": 1,
         "CI": "Callthedoctor",
         "id": "three"
      }
   ],
   "113220": [
      {
         "x": 6351,
         "y": 2516,
         "person": "person1",
         "session": "S2",
         "phase": 1,
         "quartiles": 4,
         "angle": -264.179232,
         "interpolated": 0,
         "CI": "Callthedoctor",
         "id": "one"
      },
      {
         "x": 6592,
         "y": 2843,
         "person": "person2",
         "session": "S2",
         "phase": 1,
         "quartiles": 4,
         "angle": -65.3055102,
         "interpolated": 0,
         "CI": "Callthedoctor",
         "id": "two"
      },
      {
         "x": 6768.6,
         "y": 2956.8,
         "person": "person3",
         "session": "S2",
         "phase": 1,
         "quartiles": 4,
         "angle": -27.834057,
         "interpolated": 1,
         "CI": "Callthedoctor",
         "id": "three"
      }
   ],
   "113221": [
      {
         "x": 6403.5,
         "y": 2504,
         "person": "person1",
         "session": "S2",
         "phase": 1,
         "quartiles": 4,
         "angle": -263.0906118,
         "interpolated": 1,
         "CI": "Callthedoctor",
         "id": "one"
      },
      {
         "x": 6630,
         "y": 2843,
         "person": "person2",
         "session": "S2",
         "phase": 1,
         "quartiles": 4,
         "angle": -65.3055102,
         "interpolated": 1,
         "CI": "Callthedoctor",
         "id": "two"
      },
      {
         "x": 6778.9,
         "y": 2943.7,
         "person": "person3",
         "session": "S2",
         "phase": 1,
         "quartiles": 4,
         "angle": -27.834057,
         "interpolated": 1,
         "CI": "Callthedoctor",
         "id": "three"
      }
   ],
   "113222": [
      {
         "x": 6377,
         "y": 2437,
         "person": "person1",
         "session": "S2",
         "phase": 1,
         "quartiles": 4,
         "angle": -263.606274,
         "interpolated": 0,
         "CI": "Callthedoctor",
         "id": "one"
      },
      {
         "x": 6668,
         "y": 2843,
         "person": "person2",
         "session": "S2",
         "phase": 1,
         "quartiles": 4,
         "angle": -83.5828704,
         "interpolated": 0,
         "CI": "Callthedoctor",
         "id": "two"
      },
      {
         "x": 6789.2,
         "y": 2930.6,
         "person": "person3",
         "session": "S2",
         "phase": 1,
         "quartiles": 4,
         "angle": -27.834057,
         "interpolated": 1,
         "CI": "Callthedoctor",
         "id": "three"
      }
   ],
   "113223": [
      {
         "x": 6377,
         "y": 2571,
         "person": "person1",
         "session": "S2",
         "phase": 1,
         "quartiles": 4,
         "angle": -262.746837,
         "interpolated": 0,
         "CI": "Callthedoctor",
         "id": "one"
      },
      {
         "x": 6691,
         "y": 2961,
         "person": "person2",
         "session": "S2",
         "phase": 1,
         "quartiles": 4,
         "angle": -120.4813656,
         "interpolated": 0,
         "CI": "Callthedoctor",
         "id": "two"
      },
      {
         "x": 6799.5,
         "y": 2917.5,
         "person": "person3",
         "session": "S2",
         "phase": 1,
         "quartiles": 4,
         "angle": -27.834057,
         "interpolated": 1,
         "CI": "Callthedoctor",
         "id": "three"
      }
   ],
   "113224": [
      {
         "x": 6430,
         "y": 2648,
         "person": "person1",
         "session": "S2",
         "phase": 1,
         "quartiles": 4,
         "angle": -261.8874,
         "interpolated": 0,
         "CI": "Callthedoctor",
         "id": "one"
      },
      {
         "x": 6820,
         "y": 2996,
         "person": "person2",
         "session": "S2",
         "phase": 1,
         "quartiles": 4,
         "angle": -54.3047166,
         "interpolated": 0,
         "CI": "Callthedoctor",
         "id": "two"
      },
      {
         "x": 6809.8,
         "y": 2904.4,
         "person": "person3",
         "session": "S2",
         "phase": 1,
         "quartiles": 4,
         "angle": -27.834057,
         "interpolated": 1,
         "CI": "Callthedoctor",
         "id": "three"
      }
   ],
   "113225": [
      {
         "x": 6401,
         "y": 2648,
         "person": "person1",
         "session": "S2",
         "phase": 1,
         "quartiles": 4,
         "angle": -262.460358,
         "interpolated": 0,
         "CI": "Callthedoctor",
         "id": "one"
      },
      {
         "x": 6924,
         "y": 2911,
         "person": "person2",
         "session": "S2",
         "phase": 1,
         "quartiles": 4,
         "angle": -29.7821142,
         "interpolated": 0,
         "CI": "Callthedoctor",
         "id": "two"
      },
      {
         "x": 6820.1,
         "y": 2891.3,
         "person": "person3",
         "session": "S2",
         "phase": 1,
         "quartiles": 4,
         "angle": -27.834057,
         "interpolated": 1,
         "CI": "Callthedoctor",
         "id": "three"
      }
   ],
   "113226": [
      {
         "x": 6475,
         "y": 2585,
         "person": "person1",
         "session": "S2",
         "phase": 1,
         "quartiles": 4,
         "angle": -262.0592874,
         "interpolated": 0,
         "CI": "Callthedoctor",
         "id": "one"
      },
      {
         "x": 7093,
         "y": 2911,
         "person": "person2",
         "session": "S2",
         "phase": 1,
         "quartiles": 4,
         "angle": -35.9127648,
         "interpolated": 0,
         "CI": "Callthedoctor",
         "id": "two"
      },
      {
         "x": 6830.4,
         "y": 2878.2,
         "person": "person3",
         "session": "S2",
         "phase": 1,
         "quartiles": 4,
         "angle": -27.834057,
         "interpolated": 1,
         "CI": "Callthedoctor",
         "id": "three"
      }
   ],
   "113227": [
      {
         "x": 6554,
         "y": 2686,
         "person": "person1",
         "session": "S2",
         "phase": 1,
         "quartiles": 4,
         "angle": -263.4343866,
         "interpolated": 0,
         "CI": "Callthedoctor",
         "id": "one"
      },
      {
         "x": 7093,
         "y": 2911,
         "person": "person2",
         "session": "S2",
         "phase": 1,
         "quartiles": 4,
         "angle": -35.9127648,
         "interpolated": 1,
         "CI": "Callthedoctor",
         "id": "two"
      },
      {
         "x": 6840.7,
         "y": 2865.1,
         "person": "person3",
         "session": "S2",
         "phase": 1,
         "quartiles": 4,
         "angle": -27.834057,
         "interpolated": 1,
         "CI": "Callthedoctor",
         "id": "three"
      }
   ],
   "113228": [
      {
         "x": 6685,
         "y": 2686,
         "person": "person1",
         "session": "S2",
         "phase": 1,
         "quartiles": 4,
         "angle": -262.3457664,
         "interpolated": 0,
         "CI": "Callthedoctor",
         "id": "one"
      },
      {
         "x": 7093,
         "y": 2911,
         "person": "person2",
         "session": "S2",
         "phase": 1,
         "quartiles": 4,
         "angle": -33.4490454,
         "interpolated": 0,
         "CI": "Callthedoctor",
         "id": "two"
      },
      {
         "x": 6851,
         "y": 2852,
         "person": "person3",
         "session": "S2",
         "phase": 1,
         "quartiles": 4,
         "angle": -27.834057,
         "interpolated": 1,
         "CI": "Callthedoctor",
         "id": "three"
      }
   ],
   "113229": [
      {
         "x": 6716,
         "y": 2496,
         "person": "person1",
         "session": "S2",
         "phase": 1,
         "quartiles": 4,
         "angle": -262.5749496,
         "interpolated": 0,
         "CI": "Callthedoctor",
         "id": "one"
      },
      {
         "x": 7093,
         "y": 2844,
         "person": "person2",
         "session": "S2",
         "phase": 1,
         "quartiles": 4,
         "angle": -33.563637,
         "interpolated": 0,
         "CI": "Callthedoctor",
         "id": "two"
      },
      {
         "x": 6861.3,
         "y": 2838.9,
         "person": "person3",
         "session": "S2",
         "phase": 1,
         "quartiles": 4,
         "angle": -27.834057,
         "interpolated": 1,
         "CI": "Callthedoctor",
         "id": "three"
      }
   ],
   "113230": [
      {
         "x": 6772,
         "y": 2384,
         "person": "person1",
         "session": "S2",
         "phase": 1,
         "quartiles": 4,
         "angle": -262.6322454,
         "interpolated": 0,
         "CI": "Callthedoctor",
         "id": "one"
      },
      {
         "x": 6925,
         "y": 2844,
         "person": "person2",
         "session": "S2",
         "phase": 1,
         "quartiles": 4,
         "angle": -33.5063412,
         "interpolated": 0,
         "CI": "Callthedoctor",
         "id": "two"
      },
      {
         "x": 6871.6,
         "y": 2825.8,
         "person": "person3",
         "session": "S2",
         "phase": 1,
         "quartiles": 4,
         "angle": -27.834057,
         "interpolated": 1,
         "CI": "Callthedoctor",
         "id": "three"
      }
   ],
   "113231": [
      {
         "x": 6913,
         "y": 2323,
         "person": "person1",
         "session": "S2",
         "phase": 1,
         "quartiles": 4,
         "angle": -252.3762972,
         "interpolated": 0,
         "CI": "Callthedoctor",
         "id": "one"
      },
      {
         "x": 6878,
         "y": 2765,
         "person": "person2",
         "session": "S2",
         "phase": 1,
         "quartiles": 4,
         "angle": -33.7928202,
         "interpolated": 0,
         "CI": "Callthedoctor",
         "id": "two"
      },
      {
         "x": 6881.9,
         "y": 2812.7,
         "person": "person3",
         "session": "S2",
         "phase": 1,
         "quartiles": 4,
         "angle": -27.834057,
         "interpolated": 1,
         "CI": "Callthedoctor",
         "id": "three"
      }
   ],
   "113232": [
      {
         "x": 6980,
         "y": 2377,
         "person": "person1",
         "session": "S2",
         "phase": 1,
         "quartiles": 4,
         "angle": -254.8973124,
         "interpolated": 0,
         "CI": "Callthedoctor",
         "id": "one"
      },
      {
         "x": 6860.5,
         "y": 2765,
         "person": "person2",
         "session": "S2",
         "phase": 1,
         "quartiles": 4,
         "angle": -33.7928202,
         "interpolated": 1,
         "CI": "Callthedoctor",
         "id": "two"
      },
      {
         "x": 6892.2,
         "y": 2799.6,
         "person": "person3",
         "session": "S2",
         "phase": 1,
         "quartiles": 4,
         "angle": -27.834057,
         "interpolated": 1,
         "CI": "Callthedoctor",
         "id": "three"
      }
   ],
   "113233": [
      {
         "x": 6994,
         "y": 2377,
         "person": "person1",
         "session": "S2",
         "phase": 1,
         "quartiles": 4,
         "angle": -253.6368048,
         "interpolated": 0,
         "CI": "Callthedoctor",
         "id": "one"
      },
      {
         "x": 6843,
         "y": 2765,
         "person": "person2",
         "session": "S2",
         "phase": 1,
         "quartiles": 4,
         "angle": -34.8241446,
         "interpolated": 0,
         "CI": "Callthedoctor",
         "id": "two"
      },
      {
         "x": 6902.5,
         "y": 2786.5,
         "person": "person3",
         "session": "S2",
         "phase": 1,
         "quartiles": 4,
         "angle": -27.834057,
         "interpolated": 1,
         "CI": "Callthedoctor",
         "id": "three"
      }
   ]
}